agent_deck/__init__.py
agent_deck-0.1.0.dist-info/licenses/LICENSE
agent_deck-0.1.0.dist-info/METADATA
agent_deck-0.1.0.dist-info/WHEEL
agent_deck-0.1.0.dist-info/top_level.txt
agent_deck-0.1.0.dist-info/RECORD
